zcrmsdk/.DS_Store
zcrmsdk/__init__.py
zcrmsdk/src/.DS_Store
zcrmsdk/src/__init__.py
zcrmsdk/src/json_details.json
zcrmsdk/src/com/.DS_Store
zcrmsdk/src/com/__init__.py
zcrmsdk/src/com/zoho/__init__.py
zcrmsdk/src/com/zoho/api/__init__.py
zcrmsdk/src/com/zoho/api/authenticator/__init__.py
zcrmsdk/src/com/zoho/api/authenticator/oauth_token.py
zcrmsdk/src/com/zoho/api/authenticator/token.py
zcrmsdk/src/com/zoho/api/authenticator/store/__init__.py
zcrmsdk/src/com/zoho/api/authenticator/store/db_store.py
zcrmsdk/src/com/zoho/api/authenticator/store/file_store.py
zcrmsdk/src/com/zoho/api/authenticator/store/token_store.py
zcrmsdk/src/com/zoho/api/logger/__init__.py
zcrmsdk/src/com/zoho/api/logger/logger.py
zcrmsdk/src/com/zoho/crm/__init__.py
zcrmsdk/src/com/zoho/crm/api/__init__.py
zcrmsdk/src/com/zoho/crm/api/header.py
zcrmsdk/src/com/zoho/crm/api/header_map.py
zcrmsdk/src/com/zoho/crm/api/initializer.py
zcrmsdk/src/com/zoho/crm/api/param.py
zcrmsdk/src/com/zoho/crm/api/parameter_map.py
zcrmsdk/src/com/zoho/crm/api/request_proxy.py
zcrmsdk/src/com/zoho/crm/api/sdk_config.py
zcrmsdk/src/com/zoho/crm/api/user_signature.py
zcrmsdk/src/com/zoho/crm/api/attachments/__init__.py
zcrmsdk/src/com/zoho/crm/api/attachments/action_handler.py
zcrmsdk/src/com/zoho/crm/api/attachments/action_response.py
zcrmsdk/src/com/zoho/crm/api/attachments/action_wrapper.py
zcrmsdk/src/com/zoho/crm/api/attachments/api_exception.py
zcrmsdk/src/com/zoho/crm/api/attachments/attachment.py
zcrmsdk/src/com/zoho/crm/api/attachments/attachments_operations.py
zcrmsdk/src/com/zoho/crm/api/attachments/file_body_wrapper.py
zcrmsdk/src/com/zoho/crm/api/attachments/response_handler.py
zcrmsdk/src/com/zoho/crm/api/attachments/response_wrapper.py
zcrmsdk/src/com/zoho/crm/api/attachments/success_response.py
zcrmsdk/src/com/zoho/crm/api/blue_print/__init__.py
zcrmsdk/src/com/zoho/crm/api/blue_print/action_response.py
zcrmsdk/src/com/zoho/crm/api/blue_print/api_exception.py
test_zzz_sdk-5.0.3.dist-info/METADATA
test_zzz_sdk-5.0.3.dist-info/WHEEL
test_zzz_sdk-5.0.3.dist-info/top_level.txt
test_zzz_sdk-5.0.3.dist-info/RECORD
