Metadata-Version: 2.1
Name: test-zzz-sdk
Version: 5.0.3
Summary: xxxxxxxxxx
Home-page: https://github.com/xxxxxx
Author: xxxxxxx
Author-email: xxxx@xxxxx.com
License: UNKNOWN
Keywords: xxxxxxx
Platform: UNKNOWN
Classifier: Development Status :: 5 - Production/Stable
Classifier: Intended Audience :: Developers
Classifier: Topic :: Software Development :: Build Tools
Classifier: Programming Language :: Python :: 3
Classifier: Programming Language :: Python :: 3.3
Classifier: Programming Language :: Python :: 3.4
Classifier: Programming Language :: Python :: 3.5
Classifier: Programming Language :: Python :: 3.6
Classifier: Programming Language :: Python :: 3.7
Classifier: Programming Language :: Python :: 3.8
Requires-Dist: requests
Requires-Dist: python-dateutil
Requires-Dist: urllib3
